circuit_knitting/__init__.py
circuit_knitting/cutting/__init__.py
circuit_knitting/cutting/automated_cut_finding.py
circuit_knitting/cutting/cutting_decomposition.py
circuit_knitting/cutting/cutting_experiments.py
circuit_knitting/cutting/cutting_reconstruction.py
circuit_knitting/cutting/wire_cutting_transforms.py
circuit_knitting/cutting/cut_finding/__init__.py
circuit_knitting/cutting/cut_finding/best_first_search.py
circuit_knitting/cutting/cut_finding/cco_utils.py
circuit_knitting/cutting/cut_finding/circuit_interface.py
circuit_knitting/cutting/cut_finding/cut_optimization.py
circuit_knitting/cutting/cut_finding/cutting_actions.py
circuit_knitting/cutting/cut_finding/disjoint_subcircuits_state.py
circuit_knitting/cutting/cut_finding/lo_cuts_optimizer.py
circuit_knitting/cutting/cut_finding/optimization_settings.py
circuit_knitting/cutting/cut_finding/search_space_generator.py
circuit_knitting/cutting/instructions/__init__.py
circuit_knitting/cutting/instructions/cut_wire.py
circuit_knitting/cutting/instructions/move.py
circuit_knitting/cutting/qpd/__init__.py
circuit_knitting/cutting/qpd/decompose.py
circuit_knitting/cutting/qpd/decompositions.py
circuit_knitting/cutting/qpd/qpd_basis.py
circuit_knitting/cutting/qpd/weights.py
circuit_knitting/cutting/qpd/instructions/__init__.py
circuit_knitting/cutting/qpd/instructions/qpd_gate.py
circuit_knitting/cutting/qpd/instructions/qpd_measure.py
circuit_knitting/utils/__init__.py
circuit_knitting/utils/bitwise.py
circuit_knitting/utils/iteration.py
circuit_knitting/utils/observable_grouping.py
circuit_knitting/utils/simulation.py
circuit_knitting/utils/transforms.py
circuit_knitting/utils/transpiler_passes.py
circuit_knitting_toolbox-0.8.0.dist-info/METADATA
circuit_knitting_toolbox-0.8.0.dist-info/WHEEL
circuit_knitting_toolbox-0.8.0.dist-info/licenses/LICENSE.txt
circuit_knitting_toolbox-0.8.0.dist-info/RECORD
