Metadata-Version: 2.3
Name: circuit-knitting-toolbox
Version: 0.8.0
Summary: A software prototype for a circuit knitting toolbox which connects user applications with runtime primitives
Project-URL: Documentation, https://qiskit-extensions.github.io/circuit-knitting-toolbox/
Project-URL: Repository, https://github.com/Qiskit-Extensions/circuit-knitting-toolbox
License:                     Copyright 2022 IBM and its contributors
License-File: LICENSE.txt
Classifier: Development Status :: 3 - Alpha
Classifier: Intended Audience :: Developers
Classifier: Intended Audience :: Science/Research
Classifier: License :: OSI Approved :: Apache Software License
Classifier: Natural Language :: English
Classifier: Operating System :: MacOS
Classifier: Operating System :: POSIX :: Linux
Classifier: Programming Language :: Python :: 3.8
Classifier: Programming Language :: Python :: 3.9
Classifier: Programming Language :: Python :: 3.10
Classifier: Programming Language :: Python :: 3.11
Classifier: Programming Language :: Python :: 3.12
Classifier: Topic :: Scientific/Engineering :: Physics
Requires-Python: >=3.8
Requires-Dist: numpy>=1.23.0
Requires-Dist: qiskit-aer>=0.14.0.1
Requires-Dist: qiskit-ibm-runtime>=0.23.0
Requires-Dist: qiskit<2.0,>=1.0.0
Requires-Dist: rustworkx>=0.14.0
Requires-Dist: scipy>=1.5.2
Provides-Extra: basetest
Requires-Dist: pytest-randomly>=1.2.0; extra == 'basetest'
Requires-Dist: pytest>=6.2.5; extra == 'basetest'
Provides-Extra: dev
Requires-Dist: autoflake==2.3.1; extra == 'dev'
Requires-Dist: black[jupyter]~=24.1; extra == 'dev'
Requires-Dist: ddt>=1.4.4; extra == 'dev'
Requires-Dist: mypy==1.9.0; extra == 'dev'
Requires-Dist: nbmake>=1.4.3; extra == 'dev'
Requires-Dist: nbqa>=1.6.0; extra == 'dev'
Requires-Dist: pydocstyle==6.3.0; extra == 'dev'
Requires-Dist: pylint==3.1.0; extra == 'dev'
Requires-Dist: pytest-randomly>=1.2.0; extra == 'dev'
Requires-Dist: pytest>=6.2.5; extra == 'dev'
Requires-Dist: reno>=3.4.0; extra == 'dev'
Requires-Dist: ruff==0.5.1; extra == 'dev'
Requires-Dist: toml; extra == 'dev'
Provides-Extra: docs
Requires-Dist: ipykernel>=4.5.1; extra == 'docs'
Requires-Dist: jupyter-sphinx>=0.3.2; extra == 'docs'
Requires-Dist: nbsphinx>=0.8.8; extra == 'docs'
Requires-Dist: qiskit-sphinx-theme<2,>=1.14.0; extra == 'docs'
Requires-Dist: reno>=3.4.0; extra == 'docs'
Requires-Dist: sphinx-autodoc-typehints>=1.12.0; extra == 'docs'
Requires-Dist: sphinx-copybutton>=0.5.0; extra == 'docs'
Requires-Dist: sphinx-reredirects; extra == 'docs'
Requires-Dist: sphinx>=3.0.0; extra == 'docs'
Provides-Extra: lint
Requires-Dist: autoflake==2.3.1; extra == 'lint'
Requires-Dist: black[jupyter]~=24.1; extra == 'lint'
Requires-Dist: mypy==1.9.0; extra == 'lint'
Requires-Dist: nbqa>=1.6.0; extra == 'lint'
Requires-Dist: pydocstyle==6.3.0; extra == 'lint'
Requires-Dist: pylint==3.1.0; extra == 'lint'
Requires-Dist: reno>=3.4.0; extra == 'lint'
Requires-Dist: ruff==0.5.1; extra == 'lint'
Requires-Dist: toml; extra == 'lint'
Provides-Extra: nbtest
Requires-Dist: nbmake>=1.4.3; extra == 'nbtest'
Requires-Dist: pytest-randomly>=1.2.0; extra == 'nbtest'
Requires-Dist: pytest>=6.2.5; extra == 'nbtest'
Provides-Extra: notebook-dependencies
Requires-Dist: ipywidgets; extra == 'notebook-dependencies'
Requires-Dist: matplotlib; extra == 'notebook-dependencies'
Requires-Dist: pylatexenc; extra == 'notebook-dependencies'
Provides-Extra: style
Requires-Dist: autoflake==2.3.1; extra == 'style'
Requires-Dist: black[jupyter]~=24.1; extra == 'style'
Requires-Dist: nbqa>=1.6.0; extra == 'style'
Requires-Dist: ruff==0.5.1; extra == 'style'
Provides-Extra: test
Requires-Dist: ddt>=1.4.4; extra == 'test'
Requires-Dist: pytest-randomly>=1.2.0; extra == 'test'
Requires-Dist: pytest>=6.2.5; extra == 'test'
